[
  {
    "actors": ["Emilia Clarke", "Kit Harington", "Peter Dinklage"],
    "director": "David Benioff, D.B. Weiss",
    "studio": "HBO",
    "title": "Game of Thrones",
    "synopsis": "Nove famílias nobres lutam pelo controle das terras de Westeros enquanto um inimigo antigo retorna.",
    "release_date": "2011-04-17",
    "category": "Series",
    "classification": "R",
    "duration": "73",
    "genres": ["Fantasia", "Drama", "Ação"],
    "cover": ""
  },
  {
    "actors": [],
    "director": "",
    "studio": "",
    "title": "Moonlight Mystique",
    "synopsis": "Série de mistério e fantasia envolvendo segredos ocultos sob a luz do luar.",
    "release_date": "2024-10-01",
    "category": "Series",
    "classification": "PG-13",
    "duration": "10",
    "genres": ["Mistério", "Fantasia", "Drama"],
    "cover": ""
  },
  {
    "actors": ["Úrsula Corberó", "Álvaro Morte"],
    "director": "Álex Pina",
    "studio": "Netflix",
    "title": "La Casa de Papel",
    "synopsis": "Um grupo de criminosos tenta realizar o maior assalto da história sob o comando do 'Professor'.",
    "release_date": "2017-05-02",
    "category": "Series",
    "classification": "R",
    "duration": "41",
    "genres": ["Ação", "Crime", "Drama"],
    "cover": ""
  },
  {
    "actors": ["Hailee Steinfeld"],
    "director": "Pascal Charrue, Arnaud Delord",
    "studio": "Riot Games / Fortiche",
    "title": "Arcane",
    "synopsis": "Na cidade de Piltover e Zaun, duas irmãs enfrentam forças opostas que dividem a sociedade.",
    "release_date": "2021-11-06",
    "category": "Series",
    "classification": "PG-13",
    "duration": "9",
    "genres": ["Animação", "Ação", "Ficção Científica"],
    "cover": ""
  },
  {
    "actors": ["Elizabeth Olsen", "Paul Bettany"],
    "director": "Matt Shakman",
    "studio": "Marvel Studios",
    "title": "WandaVision",
    "synopsis": "Wanda Maximoff e Visão vivem uma vida suburbana ideal até que eventos misteriosos começam a ocorrer.",
    "release_date": "2021-01-15",
    "category": "Series",
    "classification": "PG-13",
    "duration": "9",
    "genres": ["Super-herói", "Drama", "Mistério"],
    "cover": ""
  },
  {
    "actors": ["Penn Badgley"],
    "director": "Greg Berlanti, Sera Gamble",
    "studio": "Netflix",
    "title": "You",
    "synopsis": "Um gerente de livraria se torna obcecado por mulheres e comete crimes em nome do amor.",
    "release_date": "2018-09-09",
    "category": "Series",
    "classification": "R",
    "duration": "40",
    "genres": ["Psicológico", "Drama", "Suspense"],
    "cover": ""
  },
  {
    "actors": ["Kelsey Grammer"],
    "director": "James Burrows",
    "studio": "NBC",
    "title": "Frasier",
    "synopsis": "O psiquiatra Frasier Crane retorna a Seattle e recomeça a vida com seu pai e irmão.",
    "release_date": "1993-09-16",
    "category": "Series",
    "classification": "PG",
    "duration": "264",
    "genres": ["Comédia", "Drama"],
    "cover": ""
  },
  {
    "actors": ["Blake Lively", "Leighton Meester"],
    "director": "Josh Schwartz, Stephanie Savage",
    "studio": "The CW",
    "title": "Gossip Girl",
    "synopsis": "A elite adolescente de Manhattan tem seus segredos expostos por um blogueiro anônimo.",
    "release_date": "2007-09-19",
    "category": "Series",
    "classification": "PG-13",
    "duration": "121",
    "genres": ["Drama", "Romance"],
    "cover": ""
  },
  {
    "actors": ["Jim Parsons", "Johnny Galecki", "Kaley Cuoco"],
    "director": "Chuck Lorre, Bill Prady",
    "studio": "CBS",
    "title": "Big Bang: A Teoria",
    "synopsis": "Dois físicos socialmente desajustados têm suas vidas viradas do avesso por uma vizinha extrovertida.",
    "release_date": "2007-09-24",
    "category": "Series",
    "classification": "PG",
    "duration": "279",
    "genres": ["Comédia"],
    "cover": ""
  },
  {
    "actors": ["Jennifer Aniston", "Courteney Cox", "Matthew Perry"],
    "director": "David Crane, Marta Kauffman",
    "studio": "NBC",
    "title": "Friends",
    "synopsis": "Seis amigos vivem altos e baixos da vida em Nova York.",
    "release_date": "1994-09-22",
    "category": "Series",
    "classification": "PG-13",
    "duration": "236",
    "genres": ["Comédia", "Romance"],
    "cover": ""
  },
  {
    "actors": ["Andrew Lincoln", "Norman Reedus"],
    "director": "Frank Darabont",
    "studio": "AMC",
    "title": "The Walking Dead",
    "synopsis": "Um grupo luta para sobreviver em um mundo pós-apocalíptico infestado de zumbis.",
    "release_date": "2010-10-31",
    "category": "Series",
    "classification": "R",
    "duration": "177",
    "genres": ["Terror", "Drama", "Ação"],
    "cover": ""
  },
  {
    "actors": ["Elisabeth Moss"],
    "director": "Bruce Miller",
    "studio": "Hulu",
    "title": "O Conto da Aia",
    "synopsis": "Em um futuro distópico, mulheres são forçadas à servidão reprodutiva sob um regime totalitário.",
    "release_date": "2017-04-26",
    "category": "Series",
    "classification": "R",
    "duration": "56",
    "genres": ["Drama", "Distopia", "Suspense"],
    "cover": ""
  }
]
